README.md
setup.cfg
setup.py
src/plotinpy/__init__.py
src/plotinpy/pandas.py
src/plotinpy/pyplot.py
src/plotinpy/styling.py
src/plotinpy/utils.py
src/plotinpy.egg-info/PKG-INFO
src/plotinpy.egg-info/SOURCES.txt
src/plotinpy.egg-info/dependency_links.txt
src/plotinpy.egg-info/requires.txt
src/plotinpy.egg-info/top_level.txt