Metadata-Version: 2.1
Name: plotinpy
Version: 0.1.0
Summary: PlotInPy is a collection of plotting functions made on top of MatPlotLib.
Home-page: https://github.com/masbicudo/PlotInPy
Author: MASBicudo
Author-email: masbicudo@gmail.com
License: apache-2.0
Platform: UNKNOWN
Classifier: Programming Language :: Python :: 3
Classifier: License :: OSI Approved :: Apache Software License
Classifier: Operating System :: OS Independent
Provides-Extra: Use-Pandas-DataFrame
